[
 {
  "Description": "Identified a Discord client ID, which may lead to unauthorized integrations and data exposure in Discord applications.",
  "StartLine": 27,
  "EndLine": 27,
  "StartColumn": 28,
  "EndColumn": 61,
  "Match": "discord_id == \"669276074563666347\"",
  "Secret": "669276074563666347",
  "File": "tests/test_user.py",
  "SymlinkFile": "",
  "Commit": "7522882299ff338c63e58ebe64c69e4a18168211",
  "Entropy": 2.5917933,
  "Author": "Jonathan Styles",
  "Email": "64489881+jontyms@users.noreply.github.com",
  "Date": "2024-05-27T19:01:27Z",
  "Message": "Switch to SQLModel Database stuff  (#93)",
  "Tags": [],
  "RuleID": "discord-client-id",
  "Fingerprint": "7522882299ff338c63e58ebe64c69e4a18168211:tests/test_user.py:discord-client-id:27"
 },
 {
  "Description": "Identified a Discord client ID, which may lead to unauthorized integrations and data exposure in Discord applications.",
  "StartLine": 56,
  "EndLine": 56,
  "StartColumn": 10,
  "EndColumn": 40,
  "Match": "discord_id=\"669276074563666347\"",
  "Secret": "669276074563666347",
  "File": "tests/conftest.py",
  "SymlinkFile": "",
  "Commit": "7522882299ff338c63e58ebe64c69e4a18168211",
  "Entropy": 2.5917933,
  "Author": "Jonathan Styles",
  "Email": "64489881+jontyms@users.noreply.github.com",
  "Date": "2024-05-27T19:01:27Z",
  "Message": "Switch to SQLModel Database stuff  (#93)",
  "Tags": [],
  "RuleID": "discord-client-id",
  "Fingerprint": "7522882299ff338c63e58ebe64c69e4a18168211:tests/conftest.py:discord-client-id:56"
 }
]
